setup.py
breadcrumb_trail/__init__.py
breadcrumb_trail/breadcrumbs.py
breadcrumb_trail/models.py
breadcrumb_trail/tests.py
breadcrumb_trail/urls.py
breadcrumb_trail/views.py
breadcrumb_trail/templatetags/__init__.py
breadcrumb_trail/templatetags/breadcrumbs.py
django_breadcrumb_trail.egg-info/PKG-INFO
django_breadcrumb_trail.egg-info/SOURCES.txt
django_breadcrumb_trail.egg-info/dependency_links.txt
django_breadcrumb_trail.egg-info/top_level.txt