Metadata-Version: 1.0
Name: django-breadcrumb-trail
Version: 0.9.0
Summary: Drop dead simple breadcrumb trails for Django
Home-page: http://github.com/tomchristie/django-breadcrumb-trail/
Author: Tom Christie
Author-email: tom@tomchristie.com
License: BSD
Platform: UNKNOWN
